Verilog/VerilogBM-129-140.v
/*
						-----------------------------------------------
							FIRST RESPONSE DETECTOR CIRCUIT
						-----------------------------------------------

							---------------------------------
							BEHAVIORAL MODELLING VERILOG CODE
							---------------------------------
-----------------------------------------------
Mini-Project: CO202 - Design Of Digital Systems
-----------------------------------------------
Reg.No.
Palak Singhal 	16CO129
Sharanya Kamath 16CO140
-----------------------------------------------

---------
Abstract: 
---------
The idea of this mini project is to create a circuit which determines which participant has reponded the earliest.
These type of circuits are useful in the buzzer rounds of quiz shows.

In first response rounds of quiz contests, the question is thrown open to all the teams.
The person who knows the answer hits his switch first and then answers the question. 
Sometimes two or more players hit the switch almost simultaneously and it is very difficult to detect which of
them has pressed the switch first.
________________________________________________________________________________________________________________________________________________

----------------
Functionalities
----------------
-> Inputs are accepted as the players' switch status whenever there is a change.

-> A flag variable is declared which is assigned a value of 1 as long as the switch is pressed by one player and is changed to 0 whenever         	next player presses and is kept at 0 until each player turns off the switch.

-> With the help of a switch case statement corresponding player no is selected and displayed.

-> Decimal number is also displayed along with 7 segment output for better understandability.

-> Foolproof method to determine the winner as the main code does not depend on the clock pulse difference between player responses. 

-------------------------------------------------------------------------------------------------------------------
------------------------------
Brief Description of the Code
------------------------------
-> The player vector with a high bit for the player who presses the switch first is taken as input and in an always block a reg flag is kept at   	0 as long as only 1 bit is high.

-> It changes to 0 on experiencing any further changes in the player vector.

-> In the second always block the flag bit is checked in the if statement. 

->Only if the flag bit is 1 i.e. when only 1 or none of the player presses the switch the control is transferred to the corresponding  case    and the seven segment and the corresponding integer are displayed.
      	    	  
________________________________________________________________________________________________________________________________________________


*/
module VerilogM_129_140(   
		output flag,          //flag-turns 0 as soon as another player presses the switch                      
		input [3:0]player,    // vector of 4 players 
		output [6:0]display,  // vector of output in seven segment display
		output [3:0]decimal   // output in decimal number corresponding to the winner
		);
	
	wire [3:0]player;
	reg [6:0]display;
	reg [3:0]decimal;
	reg flag;

	always @*					//Execute this case block whenever there is a change in the input
		begin
			case (player)                        
				4'b0000: flag=1'b1;	// flag bit is kept at 1 as long as only 1 or 0 player presses the switch

				4'b0011: flag=1'b0;	// flag is turned to 0 for any further cases i.e cases when more than 1 player
			                           	//presses the switch and it remains at 0 for all those cases and resets to 
				4'b0101: flag=1'b0;	//1 again when all players turn the switch off  
		
				4'b1001: flag=1'b0; 
	
				4'b0110: flag=1'b0;

				4'b1010: flag=1'b0;

				4'b1100: flag=1'b0; 
		        endcase
		end


	always @*					//Execute this case block whenever there is a change in the input
		if(flag)				//Execute following statements only if flag bit is 1                         
     			begin                           
				case (player)		// according to the number of player the corresponding case is chosen
	
				       4'b0000: begin display=7'b1111110; decimal=4'b0000; end	// when no player presses display 0
	
				       4'b0001: begin display=7'b0110000; decimal=4'b0001; end	// display changes to 1 if player 1 presses first 
		
				       4'b0010: begin display=7'b1101101; decimal=4'b0010; end	// display changes to 2 if player 2 presses first
	
				       4'b0100: begin display=7'b1111001; decimal=4'b0011; end	// display changes to 3 ifplayer 3 presses first  
	
				       4'b1000: begin display=7'b0110011; decimal=4'b0100; end	// display changes to 4 if player 4 presses first
			        endcase
    			end
	endmodule

/*x-x-x-x-x-x-x-x-x-x-x-x-x-x-x-x-x-x-x-x-x-x-x-x-x-x-x-x-x-x-x-x-x-x-x-x-x-x-x-x-x-x-x-x-x-x-x-x-x-x-x-x-x-x-x-x-x-x-x-x-x-x-x-x-x-x-x-x-x-x-*/

Verilog/Verilog-129-140.v
/*
						-----------------------------------------------
							FIRST RESPONSE DETECTOR CIRCUIT
						-----------------------------------------------

							----------------------------
							        TEST-BENCH
							----------------------------
-----------------------------------------------
Mini-Project: CO202 - Design Of Digital Systems
-----------------------------------------------
Reg.No.
Palak Singhal 	16CO129
Sharanya Kamath 16CO140
-----------------------------------------------

---------
Abstract: 
---------
The idea of this mini project is to create a circuit which determines which participant has reponded the earliest.
These type of circuits are useful in the buzzer rounds of quiz shows.

In first response rounds of quiz contests, the question is thrown open to all the teams.
The person who knows the answer hits his switch first and then answers the question. 
Sometimes two or more players hit the switch almost simultaneously and it is very difficult to detect which of
them has pressed the switch first.
________________________________________________________________________________________________________________________________________________

-----------------
Functionalities
-----------------
-> Inputs are accepted as the players' switch status whenever there is a change.

-> Enables to the latches are produced by the method of feedback. 

-> There is no need of a manual enable/reset switch as the desired conditions are produced automatically through feedback.

-> Active-low and Active-high conditions are managed appropriately.

-> Decimal number is also displayed along with 7 segment output for better understandability.

-> Foolproof method to determine the winner as the main code does not depend on the clock pulse difference between player responses. 
________________________________________________________________________________________________________________________________________________

------------------------------
Brief Description of the Code
------------------------------
-> The player vector is declared where each bit displays a player i.e player1 to player3 on travelling from lsb to msb of player vector.
   Initially all the players are assigned a 0 bit to display the start state.

->  4 TEST CASES are taken where for each test case players press their switch at an interval of 10ns which gives the order in which the bits     	player vector turn high i.e the order in which the players press the switch.
 
->  After each test case the condition where the all the players turn off their switch is displayed by turning all bits of the player vector to
    0.  

-> The output is the seven segment display and corresponding decimal for all the test cases.
________________________________________________________________________________________________________________________________________________
*/
`timescale 1ns / 1ps
module Verilog_129_140;
reg [3:0]player;					//Inputs provide by the 4 players
wire [6:0]display;					//7 bit output shown on the led display
wire [3:0]decimal; 					//for decimal output
wire flag;						//a wire flag for the behavioral model

VerilogM_129_140 uut(flag, player,display,decimal);	//instantiation of the behavioral and gatelevel module		

initial
begin
$dumpfile("VerilogBM-129-140.vcd");				//creation of a vcd file
$dumpvars(0,Verilog_129_140);

	$display("\nP1\tP2\tP3\tP4\t7segment\tDecimal display\n");
	player[0]=1'b0;					//initialization of each player to 0(tackles the condition where no player presses
	player[1]=1'b0;					//the switch
	player[2]=1'b0;
	player[3]=1'b0;
#10							//TEST CASE 1
	player[0]=1'b1;					//test case where player 1 presses it first 

#10
	player[1]=1'b1;					//then player 2 after time delay of 10 nano seconds

#10
	player[2]=1'b1;					//then player 3 after time delay of 10 nano seconds

#10
	player[3]=1'b1;					//then player 4 after time delay of 10 nano seconds

#10
	begin						//reset condition(the switch presssed returns to open state again)
	player[0]=1'b0;
	player[1]=1'b0;
	player[2]=1'b0;
	player[3]=1'b0;
	end

#10							//TEST CASE 2	
	player[1]=1'b1;					//test case where player 2 presses it first 

#10
	player[0]=1'b1;					//then player 2 after time delay of 10 nano seconds

#10
	player[2]=1'b1;					//then player 2 after time delay of 10 nano seconds

#10
	player[3]=1'b1;					//then player 2 after time delay of 10 nano seconds

#10
	begin
	player[0]=1'b0;
	player[1]=1'b0;
	player[2]=1'b0;
	player[3]=1'b0;
	end

#10							//TEST CASE 3
	player[3]=1'b1;					//test case where player 4 presses it first 

#10
	player[1]=1'b1;					//then player 2 after time delay of 10 nano seconds

#10
	player[2]=1'b1;					//then player 2 after time delay of 10 nano seconds

#10
	player[0]=1'b1;					//then player 2 after time delay of 10 nano seconds

#10
	begin
	player[0]=1'b0;
	player[1]=1'b0;
	player[2]=1'b0;
	player[3]=1'b0;
	end

#10							//TEST CASE 4
	player[2]=1'b1;					//test case where player 3 presses it first 

#10
	player[1]=1'b1;					//then player 2 after time delay of 10 nano seconds

#10
	player[0]=1'b1;					//then player 3 after time delay of 10 nano seconds

#10
	player[3]=1'b1;					//then player 4 after time delay of 10 nano seconds

end

initial
	begin
		$monitor("%b\t%b\t%b\t%b\t%7b\t\t%d\n",player[0],player[1],player[2],player[3],display,decimal);	//display statement
	end

endmodule

/*x-x-x-x-x-x-x-x-x-x-x-x-x-x-x-x-x-x-x-x-x-x-x-x-x-x-x-x-x-x-x-x-x-x-x-x-x-x-x-x-x-x-x-x-x-x-x-x-x-x-x-x-x-x-x-x-x-x-x-x-x-x-x-x-x-x-x-x-x-x-*/

Verilog/VerilogBM-129-140.vcd
$date
	Tue Nov  7 21:28:44 2017
$end
$version
	Icarus Verilog
$end
$timescale
	1ps
$end
$scope module Verilog_129_140 $end
$var wire 1 ! flag $end
$var wire 7 " display [6:0] $end
$var wire 4 # decimal [3:0] $end
$var reg 4 $ player [3:0] $end
$scope module uut $end
$var wire 4 % player [3:0] $end
$var reg 4 & decimal [3:0] $end
$var reg 7 ' display [6:0] $end
$var reg 1 ! flag $end
$upscope $end
$upscope $end
$enddefinitions $end
#0
$dumpvars
b1111110 '
b0 &
b0 %
b0 $
b0 #
b1111110 "
1!
$end
#10000
b1 #
b1 &
b110000 "
b110000 '
b1 $
b1 %
#20000
0!
b11 $
b11 %
#30000
b111 $
b111 %
#40000
b1111 $
b1111 %
#50000
b0 #
b0 &
b1111110 "
b1111110 '
1!
b0 $
b0 %
#60000
b10 #
b10 &
b1101101 "
b1101101 '
b10 $
b10 %
#70000
0!
b11 $
b11 %
#80000
b111 $
b111 %
#90000
b1111 $
b1111 %
#100000
b0 #
b0 &
b1111110 "
b1111110 '
1!
b0 $
b0 %
#110000
b100 #
b100 &
b110011 "
b110011 '
b1000 $
b1000 %
#120000
0!
b1010 $
b1010 %
#130000
b1110 $
b1110 %
#140000
b1111 $
b1111 %
#150000
b0 #
b0 &
b1111110 "
b1111110 '
1!
b0 $
b0 %
#160000
b11 #
b11 &
b1111001 "
b1111001 '
b100 $
b100 %
#170000
0!
b110 $
b110 %
#180000
b111 $
b111 %
#190000
b1111 $
b1111 %
