verilog/bistable-latch/ic7475.v

module ic7475(p2,p3,p6,p7,p13,p4,p16,p15,p10,p9);
   
  input p2,p3,p6,p7,p13,p4;
  output p16,p15,p10,p9;
  reg p16,p15,p10,p9;
 // dlatch uut1(p2,p13,p16);
 // dlatch uut2(p3,p13,p15);
 // dlatch uut3(p6,p4,p10);
 // dlatch uut4(p7,p4,p9);
  always @(p13 or p2)
  if (p13) begin
    p16 <= p2;
  end
   always @(p13 or p3)
  if (p13) begin
    p15 <= p3;
  end
  always @(p4 or p6)
  if (p4) begin
    p10 <= p6;
  end
  always @(p4 or p7)
  if (p4) begin
    p9 <= p7;
  end 
 endmodule

verilog/bistable-latch/testbench.v
`timescale 1ns/100ps
 module ic7475_tb;
 wire p16,p15,p10,p9; 
 reg p2,p3,p6,p7,p13,p4;

 ic7475 uut(p2,p3,p6,p7,p13,p4,p16,p15,p10,p9);
 initial begin
		p2=1'b0;
		p3=1'b0;
		p6=1'b0;
		p7=1'b0;
	        p13=1'b0;
                p4=1'b0;
            
		$dumpfile("ddsproject.vcd");
		$dumpvars(0,ic7475_tb);
		$monitor(" inputs = %b%b%b%b\tenable1=%d\tenable2=%d\t d1=%d\td2=%d\td3=%d\td4=%d\t",p2,p3,p6,p7,p13,p4,p16,p15,p10,p9);
               
#2 begin p2=1'b1; p3=1'b0; p6=1'b1; p7=1'b1; end
#2 begin p2=1'b0; p3=1'b0; p6=1'b1; p7=1'b0; end
#2 begin p2=1'b0; p3=1'b0; p6=1'b1; p7=1'b1; end
#2 begin p2=1'b0; p3=1'b1; p6=1'b0; p7=1'b0; end
#2 begin p2=1'b1; p3=1'b0; p6=1'b1; p7=1'b0; end
end
	
	always
          #5 p13 = ~p13;
        always
          #5 p4=~p4;

	initial #50 $finish;
 endmodule

verilog/bistable-latch/ddsproject.vcd
$date
	Sat Nov  4 21:28:23 2017
$end
$version
	Icarus Verilog
$end
$timescale
	100ps
$end
$scope module ic7475_tb $end
$var wire 1 ! p9 $end
$var wire 1 " p16 $end
$var wire 1 # p15 $end
$var wire 1 $ p10 $end
$var reg 1 % p13 $end
$var reg 1 & p2 $end
$var reg 1 ' p3 $end
$var reg 1 ( p4 $end
$var reg 1 ) p6 $end
$var reg 1 * p7 $end
$scope module uut $end
$var wire 1 % p13 $end
$var wire 1 & p2 $end
$var wire 1 ' p3 $end
$var wire 1 ( p4 $end
$var wire 1 ) p6 $end
$var wire 1 * p7 $end
$var reg 1 $ p10 $end
$var reg 1 # p15 $end
$var reg 1 " p16 $end
$var reg 1 ! p9 $end
$upscope $end
$upscope $end
$enddefinitions $end
#0
$dumpvars
0*
0)
0(
0'
0&
0%
x$
x#
x"
x!
$end
#20
1*
1)
1&
#40
0*
0&
#50
0!
1$
0#
0"
1(
1%
#60
1!
1*
#80
0!
0$
1#
0*
0)
1'
#100
1)
0'
1&
0(
0%
#150
1$
0#
1"
1(
1%
#200
0(
0%
#250
1(
1%
#300
0(
0%
#350
1(
1%
#400
0(
0%
#450
1(
1%
#500
0(
0%
